README.md
setup.cfg
setup.py
FlaskyTornado.egg-info/PKG-INFO
FlaskyTornado.egg-info/SOURCES.txt
FlaskyTornado.egg-info/dependency_links.txt
FlaskyTornado.egg-info/requires.txt
FlaskyTornado.egg-info/top_level.txt
flasky/__init__.py
flasky/app.py
flasky/cache.py
flasky/config.py
flasky/context.py
flasky/di.py
flasky/errors.py
flasky/events.py
flasky/handler.py
flasky/helpers.py
flasky/parameters.py
flasky/scheduler.py
flasky/test.py
flasky/util.py
test/test_cache.py
test/test_config.py
test/test_di_container.py
test/test_hooks.py
test/test_http_requests.py
test/test_maybe_coroutine.py
test/test_namespace.py
test/test_parameter.py
test/test_scheduler.py