Metadata-Version: 1.1
Name: FlaskyTornado
Version: 0.0.45
Summary: A microframework based on Tornado and Flask and good intentions
Home-page: UNKNOWN
Author: Ali Arda Orhan
Author-email: arda.orhan@dogantv.com.tr
License: BSD
Platform: any
Classifier: Environment :: Web Environment
Classifier: Intended Audience :: Developers
Classifier: License :: OSI Approved :: BSD License
Classifier: Operating System :: OS Independent
Classifier: Programming Language :: Python
Classifier: Programming Language :: Python :: 3
Classifier: Programming Language :: Python :: 3.5
Classifier: Topic :: Internet :: WWW/HTTP :: Dynamic Content
Classifier: Topic :: Software Development :: Libraries :: Python Modules
